genopt/__init__.py
genopt/crossover.py
genopt/datatype_inference.py
genopt/environment.py
genopt/individual.py
genopt/mutation.py
genopt/parameters.py
genopt/results.py
genopt/selection.py
genopt/utils.py
genopt-0.9.15.dist-info/LICENSE
genopt-0.9.15.dist-info/METADATA
genopt-0.9.15.dist-info/WHEEL
genopt-0.9.15.dist-info/top_level.txt
genopt-0.9.15.dist-info/RECORD
