Metadata-Version: 2.1
Name: genopt
Version: 0.9.15
Summary: Genopt: optimization with genetic algorithms
Home-page: https://github.com/unaiLopez/genopt
Author: Unai Lopez Ansoleaga
Author-email: unai19970315@gmail.com
License: MIT
Platform: UNKNOWN
Requires-Python: >=3.6
Requires-Dist: numpy (==1.21.3)
Requires-Dist: tqdm (==4.64.0)
Requires-Dist: pandas (==1.3.4)
